[
  {
    "url": "https://api.github.com/repos/bitcoin/bitcoin/issues/comments/855436986",
    "html_url": "https://github.com/bitcoin/bitcoin/pull/22173#issuecomment-855436986",
    "issue_url": "https://api.github.com/repos/bitcoin/bitcoin/issues/22173",
    "id": 855436986,
    "node_id": "MDEyOklzc3VlQ29tbWVudDg1NTQzNjk4Ng==",
    "user": {
      "login": "hebasto",
      "id": 32963518,
      "node_id": "MDQ6VXNlcjMyOTYzNTE4",
      "avatar_url": "https://avatars.githubusercontent.com/u/32963518?u=7297e8aaf9188c0cb98bc549a8a02a1dc8d59e4c&v=4",
      "gravatar_id": "",
      "url": "https://api.github.com/users/hebasto",
      "html_url": "https://github.com/hebasto",
      "followers_url": "https://api.github.com/users/hebasto/followers",
      "following_url": "https://api.github.com/users/hebasto/following{/other_user}",
      "gists_url": "https://api.github.com/users/hebasto/gists{/gist_id}",
      "starred_url": "https://api.github.com/users/hebasto/starred{/owner}{/repo}",
      "subscriptions_url": "https://api.github.com/users/hebasto/subscriptions",
      "organizations_url": "https://api.github.com/users/hebasto/orgs",
      "repos_url": "https://api.github.com/users/hebasto/repos",
      "events_url": "https://api.github.com/users/hebasto/events{/privacy}",
      "received_events_url": "https://api.github.com/users/hebasto/received_events",
      "type": "User",
      "site_admin": false
    },
    "created_at": "2021-06-06T17:56:04Z",
    "updated_at": "2021-06-06T17:56:04Z",
    "author_association": "MEMBER",
    "body": "Is this a fix for #21919?",
    "reactions": {
      "url": "https://api.github.com/repos/bitcoin/bitcoin/issues/comments/855436986/reactions",
      "total_count": 0,
      "+1": 0,
      "-1": 0,
      "laugh": 0,
      "hooray": 0,
      "confused": 0,
      "heart": 0,
      "rocket": 0,
      "eyes": 0
    },
    "performed_via_github_app": null
  },
  {
    "url": "https://api.github.com/repos/bitcoin/bitcoin/issues/comments/855437881",
    "html_url": "https://github.com/bitcoin/bitcoin/pull/22173#issuecomment-855437881",
    "issue_url": "https://api.github.com/repos/bitcoin/bitcoin/issues/22173",
    "id": 855437881,
    "node_id": "MDEyOklzc3VlQ29tbWVudDg1NTQzNzg4MQ==",
    "user": {
      "login": "achow101",
      "id": 3782274,
      "node_id": "MDQ6VXNlcjM3ODIyNzQ=",
      "avatar_url": "https://avatars.githubusercontent.com/u/3782274?u=9791e96cd4268d48e3517bac41eaf2b1d09759fd&v=4",
      "gravatar_id": "",
      "url": "https://api.github.com/users/achow101",
      "html_url": "https://github.com/achow101",
      "followers_url": "https://api.github.com/users/achow101/followers",
      "following_url": "https://api.github.com/users/achow101/following{/other_user}",
      "gists_url": "https://api.github.com/users/achow101/gists{/gist_id}",
      "starred_url": "https://api.github.com/users/achow101/starred{/owner}{/repo}",
      "subscriptions_url": "https://api.github.com/users/achow101/subscriptions",
      "organizations_url": "https://api.github.com/users/achow101/orgs",
      "repos_url": "https://api.github.com/users/achow101/repos",
      "events_url": "https://api.github.com/users/achow101/events{/privacy}",
      "received_events_url": "https://api.github.com/users/achow101/received_events",
      "type": "User",
      "site_admin": false
    },
    "created_at": "2021-06-06T18:02:33Z",
    "updated_at": "2021-06-06T18:02:33Z",
    "author_association": "MEMBER",
    "body": "> Is this a fix for #21919?\r\n\r\nIt would seem so.",
    "reactions": {
      "url": "https://api.github.com/repos/bitcoin/bitcoin/issues/comments/855437881/reactions",
      "total_count": 0,
      "+1": 0,
      "-1": 0,
      "laugh": 0,
      "hooray": 0,
      "confused": 0,
      "heart": 0,
      "rocket": 0,
      "eyes": 0
    },
    "performed_via_github_app": null
  },
  {
    "url": "https://api.github.com/repos/bitcoin/bitcoin/issues/comments/861649717",
    "html_url": "https://github.com/bitcoin/bitcoin/pull/22173#issuecomment-861649717",
    "issue_url": "https://api.github.com/repos/bitcoin/bitcoin/issues/22173",
    "id": 861649717,
    "node_id": "MDEyOklzc3VlQ29tbWVudDg2MTY0OTcxNw==",
    "user": {
      "login": "Sjors",
      "id": 10217,
      "node_id": "MDQ6VXNlcjEwMjE3",
      "avatar_url": "https://avatars.githubusercontent.com/u/10217?v=4",
      "gravatar_id": "",
      "url": "https://api.github.com/users/Sjors",
      "html_url": "https://github.com/Sjors",
      "followers_url": "https://api.github.com/users/Sjors/followers",
      "following_url": "https://api.github.com/users/Sjors/following{/other_user}",
      "gists_url": "https://api.github.com/users/Sjors/gists{/gist_id}",
      "starred_url": "https://api.github.com/users/Sjors/starred{/owner}{/repo}",
      "subscriptions_url": "https://api.github.com/users/Sjors/subscriptions",
      "organizations_url": "https://api.github.com/users/Sjors/orgs",
      "repos_url": "https://api.github.com/users/Sjors/repos",
      "events_url": "https://api.github.com/users/Sjors/events{/privacy}",
      "received_events_url": "https://api.github.com/users/Sjors/received_events",
      "type": "User",
      "site_admin": false
    },
    "created_at": "2021-06-15T16:30:06Z",
    "updated_at": "2021-06-15T16:30:06Z",
    "author_association": "MEMBER",
    "body": "Thanks. I think the reason why I missed this in #16546 is that I only tested a node downgrade. Earlier versions of Bitcoin Core will stop when they see an unrecognised wallet flag.",
    "reactions": {
      "url": "https://api.github.com/repos/bitcoin/bitcoin/issues/comments/861649717/reactions",
      "total_count": 0,
      "+1": 0,
      "-1": 0,
      "laugh": 0,
      "hooray": 0,
      "confused": 0,
      "heart": 0,
      "rocket": 0,
      "eyes": 0
    },
    "performed_via_github_app": null
  }
]