{
  "url": "https://api.github.com/repos/bitcoin/bitcoin/pulls/16821",
  "id": 315182051,
  "node_id": "MDExOlB1bGxSZXF1ZXN0MzE1MTgyMDUx",
  "html_url": "https://github.com/bitcoin/bitcoin/pull/16821",
  "diff_url": "https://github.com/bitcoin/bitcoin/pull/16821.diff",
  "patch_url": "https://github.com/bitcoin/bitcoin/pull/16821.patch",
  "issue_url": "https://api.github.com/repos/bitcoin/bitcoin/issues/16821",
  "number": 16821,
  "state": "closed",
  "locked": false,
  "title": "Fix bug where duplicate PSBT keys are accepted",
  "user": {
    "login": "erasmospunk",
    "id": 944152,
    "node_id": "MDQ6VXNlcjk0NDE1Mg==",
    "avatar_url": "https://avatars.githubusercontent.com/u/944152?v=4",
    "gravatar_id": "",
    "url": "https://api.github.com/users/erasmospunk",
    "html_url": "https://github.com/erasmospunk",
    "followers_url": "https://api.github.com/users/erasmospunk/followers",
    "following_url": "https://api.github.com/users/erasmospunk/following{/other_user}",
    "gists_url": "https://api.github.com/users/erasmospunk/gists{/gist_id}",
    "starred_url": "https://api.github.com/users/erasmospunk/starred{/owner}{/repo}",
    "subscriptions_url": "https://api.github.com/users/erasmospunk/subscriptions",
    "organizations_url": "https://api.github.com/users/erasmospunk/orgs",
    "repos_url": "https://api.github.com/users/erasmospunk/repos",
    "events_url": "https://api.github.com/users/erasmospunk/events{/privacy}",
    "received_events_url": "https://api.github.com/users/erasmospunk/received_events",
    "type": "User",
    "site_admin": false
  },
  "body": "As per the BIP 174 spec a PSBT key cannot be duplicated,\r\nhowever the current code accepts key duplication.\r\nThe PSBT key/value entries can be duplicated when the value\r\nis `empty()` or `IsNull()` for `CScript` or `CTxOut` respectively\r\nand if those key/value entries are serialized before the non-empty ones.\r\n\r\nFor example, the following PSBT, included in the test vectors,\r\ncontains a duplicate field:\r\n\r\n```\r\n// magic\r\n70736274ff\r\n\r\n// global tx\r\n//// key\r\n0100\r\n//// value\r\n2a02000000000140420f000000000017a9146e91b72d5593e7d4391e2ff44e91e985c31641f08700000000\r\n//// separator\r\n00\r\n\r\n// no inputs\r\n\r\n// outputs\r\n//// key PSBT_OUT_WITNESSSCRIPT\r\n0101\r\n//// value (empty script)\r\n00\r\n//// key PSBT_OUT_WITNESSSCRIPT (same as the above)\r\n0101\r\n//// value (an OP_RETURN script)\r\n016a\r\n//// separator\r\n00\r\n```",
  "created_at": "2019-09-07T09:31:56Z",
  "updated_at": "2019-10-09T13:18:54Z",
  "closed_at": "2019-10-09T13:18:54Z",
  "merged_at": "2019-10-09T13:18:54Z",
  "merge_commit_sha": "9743432034586385cfef87df4b377c255ed0cba8",
  "assignee": null,
  "assignees": [],
  "requested_reviewers": [
    {
      "login": "achow101",
      "id": 3782274,
      "node_id": "MDQ6VXNlcjM3ODIyNzQ=",
      "avatar_url": "https://avatars.githubusercontent.com/u/3782274?v=4",
      "gravatar_id": "",
      "url": "https://api.github.com/users/achow101",
      "html_url": "https://github.com/achow101",
      "followers_url": "https://api.github.com/users/achow101/followers",
      "following_url": "https://api.github.com/users/achow101/following{/other_user}",
      "gists_url": "https://api.github.com/users/achow101/gists{/gist_id}",
      "starred_url": "https://api.github.com/users/achow101/starred{/owner}{/repo}",
      "subscriptions_url": "https://api.github.com/users/achow101/subscriptions",
      "organizations_url": "https://api.github.com/users/achow101/orgs",
      "repos_url": "https://api.github.com/users/achow101/repos",
      "events_url": "https://api.github.com/users/achow101/events{/privacy}",
      "received_events_url": "https://api.github.com/users/achow101/received_events",
      "type": "User",
      "site_admin": false
    },
    {
      "login": "instagibbs",
      "id": 5767891,
      "node_id": "MDQ6VXNlcjU3Njc4OTE=",
      "avatar_url": "https://avatars.githubusercontent.com/u/5767891?v=4",
      "gravatar_id": "",
      "url": "https://api.github.com/users/instagibbs",
      "html_url": "https://github.com/instagibbs",
      "followers_url": "https://api.github.com/users/instagibbs/followers",
      "following_url": "https://api.github.com/users/instagibbs/following{/other_user}",
      "gists_url": "https://api.github.com/users/instagibbs/gists{/gist_id}",
      "starred_url": "https://api.github.com/users/instagibbs/starred{/owner}{/repo}",
      "subscriptions_url": "https://api.github.com/users/instagibbs/subscriptions",
      "organizations_url": "https://api.github.com/users/instagibbs/orgs",
      "repos_url": "https://api.github.com/users/instagibbs/repos",
      "events_url": "https://api.github.com/users/instagibbs/events{/privacy}",
      "received_events_url": "https://api.github.com/users/instagibbs/received_events",
      "type": "User",
      "site_admin": false
    }
  ],
  "requested_teams": [],
  "labels": [
    {
      "id": 64585,
      "node_id": "MDU6TGFiZWw2NDU4NQ==",
      "url": "https://api.github.com/repos/bitcoin/bitcoin/labels/Bug",
      "name": "Bug",
      "color": "FBBAAB",
      "default": false,
      "description": null
    },
    {
      "id": 98279177,
      "node_id": "MDU6TGFiZWw5ODI3OTE3Nw==",
      "url": "https://api.github.com/repos/bitcoin/bitcoin/labels/RPC/REST/ZMQ",
      "name": "RPC/REST/ZMQ",
      "color": "0052cc",
      "default": false,
      "description": null
    }
  ],
  "milestone": null,
  "draft": false,
  "commits_url": "https://api.github.com/repos/bitcoin/bitcoin/pulls/16821/commits",
  "review_comments_url": "https://api.github.com/repos/bitcoin/bitcoin/pulls/16821/comments",
  "review_comment_url": "https://api.github.com/repos/bitcoin/bitcoin/pulls/comments{/number}",
  "comments_url": "https://api.github.com/repos/bitcoin/bitcoin/issues/16821/comments",
  "statuses_url": "https://api.github.com/repos/bitcoin/bitcoin/statuses/9743432034586385cfef87df4b377c255ed0cba8",
  "head": {
    "label": "erasmospunk:psbt-fix",
    "ref": "psbt-fix",
    "sha": "9743432034586385cfef87df4b377c255ed0cba8",
    "user": {
      "login": "erasmospunk",
      "id": 944152,
      "node_id": "MDQ6VXNlcjk0NDE1Mg==",
      "avatar_url": "https://avatars.githubusercontent.com/u/944152?v=4",
      "gravatar_id": "",
      "url": "https://api.github.com/users/erasmospunk",
      "html_url": "https://github.com/erasmospunk",
      "followers_url": "https://api.github.com/users/erasmospunk/followers",
      "following_url": "https://api.github.com/users/erasmospunk/following{/other_user}",
      "gists_url": "https://api.github.com/users/erasmospunk/gists{/gist_id}",
      "starred_url": "https://api.github.com/users/erasmospunk/starred{/owner}{/repo}",
      "subscriptions_url": "https://api.github.com/users/erasmospunk/subscriptions",
      "organizations_url": "https://api.github.com/users/erasmospunk/orgs",
      "repos_url": "https://api.github.com/users/erasmospunk/repos",
      "events_url": "https://api.github.com/users/erasmospunk/events{/privacy}",
      "received_events_url": "https://api.github.com/users/erasmospunk/received_events",
      "type": "User",
      "site_admin": false
    },
    "repo": {
      "id": 206857506,
      "node_id": "MDEwOlJlcG9zaXRvcnkyMDY4NTc1MDY=",
      "name": "bitcoin",
      "full_name": "erasmospunk/bitcoin",
      "private": false,
      "owner": {
        "login": "erasmospunk",
        "id": 944152,
        "node_id": "MDQ6VXNlcjk0NDE1Mg==",
        "avatar_url": "https://avatars.githubusercontent.com/u/944152?v=4",
        "gravatar_id": "",
        "url": "https://api.github.com/users/erasmospunk",
        "html_url": "https://github.com/erasmospunk",
        "followers_url": "https://api.github.com/users/erasmospunk/followers",
        "following_url": "https://api.github.com/users/erasmospunk/following{/other_user}",
        "gists_url": "https://api.github.com/users/erasmospunk/gists{/gist_id}",
        "starred_url": "https://api.github.com/users/erasmospunk/starred{/owner}{/repo}",
        "subscriptions_url": "https://api.github.com/users/erasmospunk/subscriptions",
        "organizations_url": "https://api.github.com/users/erasmospunk/orgs",
        "repos_url": "https://api.github.com/users/erasmospunk/repos",
        "events_url": "https://api.github.com/users/erasmospunk/events{/privacy}",
        "received_events_url": "https://api.github.com/users/erasmospunk/received_events",
        "type": "User",
        "site_admin": false
      },
      "html_url": "https://github.com/erasmospunk/bitcoin",
      "description": "Bitcoin Core integration/staging tree",
      "fork": true,
      "url": "https://api.github.com/repos/erasmospunk/bitcoin",
      "forks_url": "https://api.github.com/repos/erasmospunk/bitcoin/forks",
      "keys_url": "https://api.github.com/repos/erasmospunk/bitcoin/keys{/key_id}",
      "collaborators_url": "https://api.github.com/repos/erasmospunk/bitcoin/collaborators{/collaborator}",
      "teams_url": "https://api.github.com/repos/erasmospunk/bitcoin/teams",
      "hooks_url": "https://api.github.com/repos/erasmospunk/bitcoin/hooks",
      "issue_events_url": "https://api.github.com/repos/erasmospunk/bitcoin/issues/events{/number}",
      "events_url": "https://api.github.com/repos/erasmospunk/bitcoin/events",
      "assignees_url": "https://api.github.com/repos/erasmospunk/bitcoin/assignees{/user}",
      "branches_url": "https://api.github.com/repos/erasmospunk/bitcoin/branches{/branch}",
      "tags_url": "https://api.github.com/repos/erasmospunk/bitcoin/tags",
      "blobs_url": "https://api.github.com/repos/erasmospunk/bitcoin/git/blobs{/sha}",
      "git_tags_url": "https://api.github.com/repos/erasmospunk/bitcoin/git/tags{/sha}",
      "git_refs_url": "https://api.github.com/repos/erasmospunk/bitcoin/git/refs{/sha}",
      "trees_url": "https://api.github.com/repos/erasmospunk/bitcoin/git/trees{/sha}",
      "statuses_url": "https://api.github.com/repos/erasmospunk/bitcoin/statuses/{sha}",
      "languages_url": "https://api.github.com/repos/erasmospunk/bitcoin/languages",
      "stargazers_url": "https://api.github.com/repos/erasmospunk/bitcoin/stargazers",
      "contributors_url": "https://api.github.com/repos/erasmospunk/bitcoin/contributors",
      "subscribers_url": "https://api.github.com/repos/erasmospunk/bitcoin/subscribers",
      "subscription_url": "https://api.github.com/repos/erasmospunk/bitcoin/subscription",
      "commits_url": "https://api.github.com/repos/erasmospunk/bitcoin/commits{/sha}",
      "git_commits_url": "https://api.github.com/repos/erasmospunk/bitcoin/git/commits{/sha}",
      "comments_url": "https://api.github.com/repos/erasmospunk/bitcoin/comments{/number}",
      "issue_comment_url": "https://api.github.com/repos/erasmospunk/bitcoin/issues/comments{/number}",
      "contents_url": "https://api.github.com/repos/erasmospunk/bitcoin/contents/{+path}",
      "compare_url": "https://api.github.com/repos/erasmospunk/bitcoin/compare/{base}...{head}",
      "merges_url": "https://api.github.com/repos/erasmospunk/bitcoin/merges",
      "archive_url": "https://api.github.com/repos/erasmospunk/bitcoin/{archive_format}{/ref}",
      "downloads_url": "https://api.github.com/repos/erasmospunk/bitcoin/downloads",
      "issues_url": "https://api.github.com/repos/erasmospunk/bitcoin/issues{/number}",
      "pulls_url": "https://api.github.com/repos/erasmospunk/bitcoin/pulls{/number}",
      "milestones_url": "https://api.github.com/repos/erasmospunk/bitcoin/milestones{/number}",
      "notifications_url": "https://api.github.com/repos/erasmospunk/bitcoin/notifications{?since,all,participating}",
      "labels_url": "https://api.github.com/repos/erasmospunk/bitcoin/labels{/name}",
      "releases_url": "https://api.github.com/repos/erasmospunk/bitcoin/releases{/id}",
      "deployments_url": "https://api.github.com/repos/erasmospunk/bitcoin/deployments",
      "created_at": "2019-09-06T19:03:29Z",
      "updated_at": "2019-09-06T19:03:36Z",
      "pushed_at": "2019-10-07T22:45:54Z",
      "git_url": "git://github.com/erasmospunk/bitcoin.git",
      "ssh_url": "git@github.com:erasmospunk/bitcoin.git",
      "clone_url": "https://github.com/erasmospunk/bitcoin.git",
      "svn_url": "https://github.com/erasmospunk/bitcoin",
      "homepage": "https://bitcoincore.org/en/download",
      "size": 135238,
      "stargazers_count": 0,
      "watchers_count": 0,
      "language": null,
      "has_issues": false,
      "has_projects": true,
      "has_downloads": false,
      "has_wiki": false,
      "has_pages": false,
      "forks_count": 0,
      "mirror_url": null,
      "archived": false,
      "disabled": false,
      "open_issues_count": 0,
      "license": {
        "key": "mit",
        "name": "MIT License",
        "spdx_id": "MIT",
        "url": "https://api.github.com/licenses/mit",
        "node_id": "MDc6TGljZW5zZTEz"
      },
      "allow_forking": true,
      "is_template": false,
      "topics": [],
      "visibility": "public",
      "forks": 0,
      "open_issues": 0,
      "watchers": 0,
      "default_branch": "master"
    }
  },
  "base": {
    "label": "bitcoin:master",
    "ref": "master",
    "sha": "febc31c641b6930f6dc9a97d9492c868ae032bc3",
    "user": {
      "login": "bitcoin",
      "id": 528860,
      "node_id": "MDEyOk9yZ2FuaXphdGlvbjUyODg2MA==",
      "avatar_url": "https://avatars.githubusercontent.com/u/528860?v=4",
      "gravatar_id": "",
      "url": "https://api.github.com/users/bitcoin",
      "html_url": "https://github.com/bitcoin",
      "followers_url": "https://api.github.com/users/bitcoin/followers",
      "following_url": "https://api.github.com/users/bitcoin/following{/other_user}",
      "gists_url": "https://api.github.com/users/bitcoin/gists{/gist_id}",
      "starred_url": "https://api.github.com/users/bitcoin/starred{/owner}{/repo}",
      "subscriptions_url": "https://api.github.com/users/bitcoin/subscriptions",
      "organizations_url": "https://api.github.com/users/bitcoin/orgs",
      "repos_url": "https://api.github.com/users/bitcoin/repos",
      "events_url": "https://api.github.com/users/bitcoin/events{/privacy}",
      "received_events_url": "https://api.github.com/users/bitcoin/received_events",
      "type": "Organization",
      "site_admin": false
    },
    "repo": {
      "id": 1181927,
      "node_id": "MDEwOlJlcG9zaXRvcnkxMTgxOTI3",
      "name": "bitcoin",
      "full_name": "bitcoin/bitcoin",
      "private": false,
      "owner": {
        "login": "bitcoin",
        "id": 528860,
        "node_id": "MDEyOk9yZ2FuaXphdGlvbjUyODg2MA==",
        "avatar_url": "https://avatars.githubusercontent.com/u/528860?v=4",
        "gravatar_id": "",
        "url": "https://api.github.com/users/bitcoin",
        "html_url": "https://github.com/bitcoin",
        "followers_url": "https://api.github.com/users/bitcoin/followers",
        "following_url": "https://api.github.com/users/bitcoin/following{/other_user}",
        "gists_url": "https://api.github.com/users/bitcoin/gists{/gist_id}",
        "starred_url": "https://api.github.com/users/bitcoin/starred{/owner}{/repo}",
        "subscriptions_url": "https://api.github.com/users/bitcoin/subscriptions",
        "organizations_url": "https://api.github.com/users/bitcoin/orgs",
        "repos_url": "https://api.github.com/users/bitcoin/repos",
        "events_url": "https://api.github.com/users/bitcoin/events{/privacy}",
        "received_events_url": "https://api.github.com/users/bitcoin/received_events",
        "type": "Organization",
        "site_admin": false
      },
      "html_url": "https://github.com/bitcoin/bitcoin",
      "description": "Bitcoin Core integration/staging tree",
      "fork": false,
      "url": "https://api.github.com/repos/bitcoin/bitcoin",
      "forks_url": "https://api.github.com/repos/bitcoin/bitcoin/forks",
      "keys_url": "https://api.github.com/repos/bitcoin/bitcoin/keys{/key_id}",
      "collaborators_url": "https://api.github.com/repos/bitcoin/bitcoin/collaborators{/collaborator}",
      "teams_url": "https://api.github.com/repos/bitcoin/bitcoin/teams",
      "hooks_url": "https://api.github.com/repos/bitcoin/bitcoin/hooks",
      "issue_events_url": "https://api.github.com/repos/bitcoin/bitcoin/issues/events{/number}",
      "events_url": "https://api.github.com/repos/bitcoin/bitcoin/events",
      "assignees_url": "https://api.github.com/repos/bitcoin/bitcoin/assignees{/user}",
      "branches_url": "https://api.github.com/repos/bitcoin/bitcoin/branches{/branch}",
      "tags_url": "https://api.github.com/repos/bitcoin/bitcoin/tags",
      "blobs_url": "https://api.github.com/repos/bitcoin/bitcoin/git/blobs{/sha}",
      "git_tags_url": "https://api.github.com/repos/bitcoin/bitcoin/git/tags{/sha}",
      "git_refs_url": "https://api.github.com/repos/bitcoin/bitcoin/git/refs{/sha}",
      "trees_url": "https://api.github.com/repos/bitcoin/bitcoin/git/trees{/sha}",
      "statuses_url": "https://api.github.com/repos/bitcoin/bitcoin/statuses/{sha}",
      "languages_url": "https://api.github.com/repos/bitcoin/bitcoin/languages",
      "stargazers_url": "https://api.github.com/repos/bitcoin/bitcoin/stargazers",
      "contributors_url": "https://api.github.com/repos/bitcoin/bitcoin/contributors",
      "subscribers_url": "https://api.github.com/repos/bitcoin/bitcoin/subscribers",
      "subscription_url": "https://api.github.com/repos/bitcoin/bitcoin/subscription",
      "commits_url": "https://api.github.com/repos/bitcoin/bitcoin/commits{/sha}",
      "git_commits_url": "https://api.github.com/repos/bitcoin/bitcoin/git/commits{/sha}",
      "comments_url": "https://api.github.com/repos/bitcoin/bitcoin/comments{/number}",
      "issue_comment_url": "https://api.github.com/repos/bitcoin/bitcoin/issues/comments{/number}",
      "contents_url": "https://api.github.com/repos/bitcoin/bitcoin/contents/{+path}",
      "compare_url": "https://api.github.com/repos/bitcoin/bitcoin/compare/{base}...{head}",
      "merges_url": "https://api.github.com/repos/bitcoin/bitcoin/merges",
      "archive_url": "https://api.github.com/repos/bitcoin/bitcoin/{archive_format}{/ref}",
      "downloads_url": "https://api.github.com/repos/bitcoin/bitcoin/downloads",
      "issues_url": "https://api.github.com/repos/bitcoin/bitcoin/issues{/number}",
      "pulls_url": "https://api.github.com/repos/bitcoin/bitcoin/pulls{/number}",
      "milestones_url": "https://api.github.com/repos/bitcoin/bitcoin/milestones{/number}",
      "notifications_url": "https://api.github.com/repos/bitcoin/bitcoin/notifications{?since,all,participating}",
      "labels_url": "https://api.github.com/repos/bitcoin/bitcoin/labels{/name}",
      "releases_url": "https://api.github.com/repos/bitcoin/bitcoin/releases{/id}",
      "deployments_url": "https://api.github.com/repos/bitcoin/bitcoin/deployments",
      "created_at": "2010-12-19T15:16:43Z",
      "updated_at": "2021-12-02T09:59:34Z",
      "pushed_at": "2021-12-02T09:35:21Z",
      "git_url": "git://github.com/bitcoin/bitcoin.git",
      "ssh_url": "git@github.com:bitcoin/bitcoin.git",
      "clone_url": "https://github.com/bitcoin/bitcoin.git",
      "svn_url": "https://github.com/bitcoin/bitcoin",
      "homepage": "https://bitcoincore.org/en/download",
      "size": 188203,
      "stargazers_count": 59736,
      "watchers_count": 59736,
      "language": "C++",
      "has_issues": true,
      "has_projects": true,
      "has_downloads": false,
      "has_wiki": false,
      "has_pages": false,
      "forks_count": 30710,
      "mirror_url": null,
      "archived": false,
      "disabled": false,
      "open_issues_count": 1020,
      "license": {
        "key": "mit",
        "name": "MIT License",
        "spdx_id": "MIT",
        "url": "https://api.github.com/licenses/mit",
        "node_id": "MDc6TGljZW5zZTEz"
      },
      "allow_forking": true,
      "is_template": false,
      "topics": [
        "bitcoin",
        "c-plus-plus",
        "cryptocurrency",
        "cryptography",
        "p2p"
      ],
      "visibility": "public",
      "forks": 30710,
      "open_issues": 1020,
      "watchers": 59736,
      "default_branch": "master"
    }
  },
  "_links": {
    "self": {
      "href": "https://api.github.com/repos/bitcoin/bitcoin/pulls/16821"
    },
    "html": {
      "href": "https://github.com/bitcoin/bitcoin/pull/16821"
    },
    "issue": {
      "href": "https://api.github.com/repos/bitcoin/bitcoin/issues/16821"
    },
    "comments": {
      "href": "https://api.github.com/repos/bitcoin/bitcoin/issues/16821/comments"
    },
    "review_comments": {
      "href": "https://api.github.com/repos/bitcoin/bitcoin/pulls/16821/comments"
    },
    "review_comment": {
      "href": "https://api.github.com/repos/bitcoin/bitcoin/pulls/comments{/number}"
    },
    "commits": {
      "href": "https://api.github.com/repos/bitcoin/bitcoin/pulls/16821/commits"
    },
    "statuses": {
      "href": "https://api.github.com/repos/bitcoin/bitcoin/statuses/9743432034586385cfef87df4b377c255ed0cba8"
    }
  },
  "author_association": "CONTRIBUTOR",
  "auto_merge": null,
  "active_lock_reason": null,
  "merged": true,
  "mergeable": null,
  "rebaseable": null,
  "mergeable_state": "unknown",
  "merged_by": {
    "login": "fanquake",
    "id": 863730,
    "node_id": "MDQ6VXNlcjg2MzczMA==",
    "avatar_url": "https://avatars.githubusercontent.com/u/863730?v=4",
    "gravatar_id": "",
    "url": "https://api.github.com/users/fanquake",
    "html_url": "https://github.com/fanquake",
    "followers_url": "https://api.github.com/users/fanquake/followers",
    "following_url": "https://api.github.com/users/fanquake/following{/other_user}",
    "gists_url": "https://api.github.com/users/fanquake/gists{/gist_id}",
    "starred_url": "https://api.github.com/users/fanquake/starred{/owner}{/repo}",
    "subscriptions_url": "https://api.github.com/users/fanquake/subscriptions",
    "organizations_url": "https://api.github.com/users/fanquake/orgs",
    "repos_url": "https://api.github.com/users/fanquake/repos",
    "events_url": "https://api.github.com/users/fanquake/events{/privacy}",
    "received_events_url": "https://api.github.com/users/fanquake/received_events",
    "type": "User",
    "site_admin": false
  },
  "comments": 9,
  "review_comments": 3,
  "maintainer_can_modify": false,
  "commits": 1,
  "additions": 28,
  "deletions": 11,
  "changed_files": 2
}